tests/__init__.py
tests/emg.py
tests/unit_test_all.py
tests/unit_test_analytical_jacobian.py
tests/unit_test_parallel.py
tests/unit_test_raw_fit.py
tests/unit_test_skewed_gaussian.py
torchimize/__init__.py
torchimize/functions/__init__.py
torchimize/functions/fun_dims.py
torchimize/functions/jacobian.py
torchimize/functions/parallel/__init__.py
torchimize/functions/parallel/gda_fun_parallel.py
torchimize/functions/parallel/gna_fun_parallel.py
torchimize/functions/parallel/lma_fun_parallel.py
torchimize/functions/parallel/newton_parallel.py
torchimize/functions/single/__init__.py
torchimize/functions/single/gda_fun_single.py
torchimize/functions/single/gna_fun_single.py
torchimize/functions/single/lma_fun_single.py
torchimize/optimizer/__init__.py
torchimize/optimizer/gna_opt.py
torchimize-0.0.16.dist-info/LICENSE.md
torchimize-0.0.16.dist-info/METADATA
torchimize-0.0.16.dist-info/WHEEL
torchimize-0.0.16.dist-info/top_level.txt
torchimize-0.0.16.dist-info/RECORD
