Metadata-Version: 2.1
Name: torchimize
Version: 0.0.16
Summary: Optimization Algorithms using Pytorch
Home-page: http://github.com/hahnec/torchimize
Author: Christopher Hahne
Author-email: inbox@christopherhahne.de
License: GNU GPL V3.0
Keywords: pytorch torch optimization mathematical linear programming gauss newton levenberg marquardt
Platform: UNKNOWN
Requires-Dist: torch >=1.11.0
Requires-Dist: scikit-learn >=1.0.1
Requires-Dist: docutils >=0.18.1
